pyhomekit/__init__.py
pyhomekit/ble.py
pyhomekit/constants.py
pyhomekit/utils.py
pyhomekit-0.0.1.2.dist-info/DESCRIPTION.rst
pyhomekit-0.0.1.2.dist-info/METADATA
pyhomekit-0.0.1.2.dist-info/RECORD
pyhomekit-0.0.1.2.dist-info/WHEEL
pyhomekit-0.0.1.2.dist-info/metadata.json
pyhomekit-0.0.1.2.dist-info/top_level.txt
